cotede/__init__.py
cotede/datasets.py
cotede/misc.py
cotede/qc.py
cotede/version.py
cotede/anomaly_detection/__init__.py
cotede/anomaly_detection/anomaly_detection.py
cotede/fuzzy/LICENSE_scikit-fuzzy.txt
cotede/fuzzy/__init__.py
cotede/fuzzy/defuzz.py
cotede/fuzzy/fuzzy_core.py
cotede/fuzzy/membership_functions.py
cotede/humanqc/__init__.py
cotede/humanqc/humaneval.py
cotede/qc_cfg/anomaly_detection.json
cotede/qc_cfg/argo.json
cotede/qc_cfg/cotede.json
cotede/qc_cfg/eurogoos.json
cotede/qc_cfg/eurogoos_realtime.json
cotede/qc_cfg/fuzzylogic.json
cotede/qc_cfg/gtspp.json
cotede/qc_cfg/gtspp_realtime.json
cotede/qc_cfg/morello2014.json
cotede/qc_cfg/tsg.json
cotede/qctests/__init__.py
cotede/qctests/anomaly_detection.py
cotede/qctests/bin_spike.py
cotede/qctests/cars_normbias.py
cotede/qctests/constant_cluster_size.py
cotede/qctests/core.py
cotede/qctests/cum_rate_of_change.py
cotede/qctests/deepest_pressure.py
cotede/qctests/density_inversion.py
cotede/qctests/descentPrate.py
cotede/qctests/digit_roll_over.py
cotede/qctests/fuzzylogic.py
cotede/qctests/global_range.py
cotede/qctests/gradient.py
cotede/qctests/gradient_depthconditional.py
cotede/qctests/location_at_sea.py
cotede/qctests/monotonic_z.py
cotede/qctests/morello2014.py
cotede/qctests/possible_speed.py
cotede/qctests/profile_envelop.py
cotede/qctests/qctests.py
cotede/qctests/rate_of_change.py
cotede/qctests/regional_range.py
cotede/qctests/spike.py
cotede/qctests/spike_depthconditional.py
cotede/qctests/stuck_value.py
cotede/qctests/tukey53H.py
cotede/qctests/valid_geolocation.py
cotede/qctests/woa_normbias.py
cotede/utils/__init__.py
cotede/utils/config.py
cotede/utils/utils.py
cotede-0.23.9.dist-info/AUTHORS.rst
cotede-0.23.9.dist-info/LICENSE
cotede-0.23.9.dist-info/METADATA
cotede-0.23.9.dist-info/WHEEL
cotede-0.23.9.dist-info/top_level.txt
cotede-0.23.9.dist-info/RECORD
