Metadata-Version: 2.1
Name: cotede
Version: 0.23.9
Summary: Quality Control of Oceanographic Data
Author: Guilherme Castelão
Author-email: guilherme@castelao.net
License: Copyright (c) 2011-2023, Guilherme Pimenta Castelão
Project-URL: documentation, https://cotede.readthedocs.io
Project-URL: repository, https://github.com/castelao/cotede
Keywords: oceanography,ocean data,Quality Control,CTD
Classifier: Development Status :: 5 - Production/Stable
Classifier: Intended Audience :: Science/Research
Classifier: License :: OSI Approved :: BSD License
Classifier: Operating System :: OS Independent
Classifier: Programming Language :: Python :: 3
Classifier: Programming Language :: Python :: 3.8
Classifier: Programming Language :: Python :: 3.9
Classifier: Programming Language :: Python :: 3.10
Classifier: Programming Language :: Python :: 3.11
Classifier: Topic :: Scientific/Engineering
Requires-Python: >=3.8
License-File: LICENSE
License-File: AUTHORS.rst
Requires-Dist: Click (>=6.6)
Requires-Dist: numpy (>=1.20)
Requires-Dist: oceansdb (>=0.8.13)
Requires-Dist: scipy (>=1.0.0)
Provides-Extra: gsw
Requires-Dist: gsw (>=3.0.6) ; extra == 'gsw'
Provides-Extra: oceansdb
Requires-Dist: oceansdb (>=0.8.13) ; extra == 'oceansdb'
Provides-Extra: manualqc
Requires-Dist: matplotlib ; extra == 'manualqc'
Provides-Extra: regional
Requires-Dist: Shapely (>=1.6.4) ; extra == 'regional'
Provides-Extra: test
Requires-Dist: hypothesis (>=6.29.3) ; extra == 'test'
Requires-Dist: pytest (>=5.0.0) ; extra == 'test'
Requires-Dist: pytest-cov[all] ; extra == 'test'
Requires-Dist: pytest-xdist (>=1.29) ; extra == 'test'
Requires-Dist: pip (>=9.0.1) ; extra == 'test'
Requires-Dist: flake8 (>=3.2.1) ; extra == 'test'
Requires-Dist: tox (>=2.3.3) ; extra == 'test'
Requires-Dist: coverage (>=4.2) ; extra == 'test'
Requires-Dist: matplotlib (>=3.0) ; extra == 'test'
Requires-Dist: netCDF4 (>=1.5) ; extra == 'test'
Requires-Dist: pandas (>=1.3) ; extra == 'test'
Requires-Dist: supportdata (>=0.1.2) ; extra == 'test'
Requires-Dist: twine (>=1.8.1) ; extra == 'test'
Requires-Dist: xarray (>=2022.0) ; extra == 'test'
Requires-Dist: Sphinx (>=1.8) ; extra == 'test'
